{
    "auto": "Detectar idioma",
    "af": "Afrikáans",
    "ay": "Aimara",
    "sq": "Albanés",
    "de": "alemán",
    "am": "amhárico",
    "ar": "árabe",
    "hy": "Armenio",
    "as": "Asamés",
    "az": "azerí",
    "bm": "Bambara",
    "bn": "bengalí",
    "bho": "Bhoyapurí",
    "be": "Bielorruso",
    "my": "Birmano",
    "bs": "bosnio",
    "bg": "Búlgaro",
    "km": "Camboyano",
    "kn": "canarés",
    "ca": "catalán",
    "ceb": "Cebuano",
    "cs": "checo",
    "ny": "Chichewa",
    "zh-CN": "Chino (simplificado)",
    "zh-TW": "Chino (tradicional)",
    "si": "Cingalés",
    "ko": "coreano",
    "co": "Corso",
    "ht": "Criollo haitiano",
    "hr": "Croata",
    "da": "danés",
    "dv": "Divehi",
    "doi": "Dogri",
    "sk": "eslovaco",
    "sl": "Esloveno",
    "es": "español",
    "eo": "Esperanto",
    "et": "Estonio",
    "eu": "euskera",
    "ee": "Ewé",
    "fi": "finlandés",
    "fr": "francés",
    "fy": "frisio",
    "gd": "Gaélico escocés",
    "cy": "galés",
    "gl": "Gallego",
    "ka": "Georgiano",
    "el": "griego",
    "gn": "guaraní",
    "gu": "Gujarati",
    "ha": "Hausa",
    "haw": "Hawaiano",
    "iw": "hebreo",
    "hi": "hindi",
    "hmn": "Hmong",
    "hu": "Húngaro",
    "ig": "igbo",
    "ilo": "Ilocano",
    "id": "Indonesio",
    "en": "inglés",
    "ga": "irlandés",
    "is": "Islandés",
    "it": "italiano",
    "ja": "Japonés",
    "jw": "Javanés",
    "kk": "kazajo",
    "rw": "Kinyarwanda",
    "ky": "kirguís",
    "gom": "Konkaní",
    "kri": "Krio",
    "ku": "Kurdo (kurmanyi)",
    "ckb": "Kurdo (sorani)",
    "lo": "Lao",
    "la": "latín",
    "lv": "letón",
    "ln": "lingala",
    "lt": "Lituano",
    "lg": "Luganda",
    "lb": "Luxemburgués",
    "mk": "Macedonio",
    "mai": "Maithili",
    "ml": "Malayalam",
    "ms": "malayo",
    "mg": "Malgache",
    "mt": "maltés",
    "mi": "Maorí",
    "mr": "maratí",
    "mni-Mtei": "Meiteilon (manipuri)",
    "lus": "Mizo",
    "mn": "Mongol",
    "nl": "neerlandés",
    "ne": "nepalí",
    "no": "Noruego",
    "or": "Oriya",
    "om": "Oromo",
    "pa": "panyabí",
    "ps": "pastún",
    "fa": "persa",
    "pl": "polaco",
    "pt": "Portugués",
    "qu": "Quechua",
    "ro": "Rumano",
    "ru": "ruso",
    "sm": "Samoano",
    "sa": "Sánscrito",
    "nso": "Sepedi",
    "sr": "serbio",
    "st": "sesoto",
    "sn": "Shona",
    "sd": "sindhi",
    "so": "somalí",
    "sw": "suajili",
    "sv": "sueco",
    "su": "Sundanés",
    "tl": "Tagalo",
    "th": "tailandés",
    "ta": "tamil",
    "tt": "Tártaro",
    "tg": "tayiko",
    "te": "telugu",
    "ti": "Tigrinya",
    "ts": "Tsonga",
    "tr": "turco",
    "tk": "turkmeno",
    "ak": "Twi",
    "uk": "Ucraniano",
    "ug": "Uigur",
    "ur": "urdu",
    "uz": "uzbeco",
    "vi": "Vietnamita",
    "xh": "xhosa",
    "yi": "yidis",
    "yo": "Yoruba",
    "zu": "zulú"
}